nitter/__init__.py
nitter/exceptions.py
nitter/models.py
nitter/nitter.py
nitter-0.0.5.dist-info/LICENSE
nitter-0.0.5.dist-info/METADATA
nitter-0.0.5.dist-info/WHEEL
nitter-0.0.5.dist-info/top_level.txt
nitter-0.0.5.dist-info/RECORD
