Metadata-Version: 2.1
Name: nitter
Version: 0.0.5
Summary: Nitter is a simple library to scrap Twitter data using the Nitter website
Home-page: https://github.com/iAliF/Nitter/
Download-URL: https://github.com/iAliF/Nitter/archive/refs/tags/v0.0.5-alpha.zip
Author: Ali Fotouhi
Author-email: the.alif.dev@gmail.com 
License: MIT
Project-URL: Documentation, https://github.com/iAliF/Nitter/
Project-URL: Source, https://github.com/iAliF/Nitter/
Project-URL: Bug Tracker, https://github.com/iAliF/Nitter/issues
Keywords: Nitter,Twitter,Twitter Scraper
Classifier: Development Status :: 3 - Alpha
Classifier: Intended Audience :: Developers
Classifier: Topic :: Software Development :: Build Tools
Classifier: Topic :: Software Development :: Libraries
Classifier: Topic :: Software Development :: Libraries :: Python Modules
Classifier: License :: OSI Approved :: MIT License
Classifier: Programming Language :: Python :: 3.5
Classifier: Programming Language :: Python :: 3.6
Classifier: Programming Language :: Python :: 3.7
Classifier: Programming Language :: Python :: 3.8
Classifier: Programming Language :: Python :: 3.9
Classifier: Programming Language :: Python :: 3.10
Classifier: Programming Language :: Python :: 3.11
Classifier: Programming Language :: Python :: 3.12
Classifier: Programming Language :: Python :: 3.13
License-File: LICENSE
Requires-Dist: requests
Requires-Dist: beautifulsoup4
